{"General Info": {"Distributor": "Freestyle Releasing", "Opening": "$2,720", "Budget": ":", "Release Date": ["Jul 31, 2020", "Running Time", "1 hr 50 min"], "MPAA": ":", "Genres": ["Thriller"], "In Release": "227 days/32 weeks", "Widest Release": "8 theaters"}, "Weekly Income": [{"range": "Jul 31-Aug 6", "rank": "10", "weekly": "$3,931", "lw": "-", "theaters": "8", "change": "-", "avg": "$491", "todate": "$3,931", "week": "1"}, {"range": "Aug 7-13", "rank": "15", "weekly": "$2,242", "lw": "-43%", "theaters": "7", "change": "-1", "avg": "$320", "todate": "$6,173", "week": "2"}, {"range": "Aug 14-20", "rank": "23", "weekly": "$803", "lw": "-64.2%", "theaters": "6", "change": "-1", "avg": "$133", "todate": "$6,976", "week": "3"}]}