{"General Info": {"Distributor": "Walt Disney Studios Motion Pictures", "Opening": "$75,000", "Budget": "$11,000,000", "Release Date": ["Jan 1, 2021", "MPAA", "R"], "MPAA": "R", "Genres": ["Horror", "Sci-Fi"], "In Release": "73 days/10 weeks", "Widest Release": "505 theaters"}, "Weekly Income": [{"range": "Jan 1-7", "rank": "11", "weekly": "$75,000", "lw": "-", "theaters": "505", "change": "-", "avg": "$148", "todate": "$75,000", "week": "1"}, {"range": "Jan 8-14", "rank": "12", "weekly": "$60,000", "lw": "-20%", "theaters": "456", "change": "-49", "avg": "$131", "todate": "$135,000", "week": "2"}]}