[{"range": "Nov 20-26", "rank": "2", "weekly": "$60,127,477", "lw": "-", "theaters": "3,140", "change": "-", "avg": "$19,148", "todate": "$60,127,477", "week": "1"}, {"range": "Nov 27-Dec 3", "rank": "2", "weekly": "$48,696,901", "lw": "-19%", "theaters": "3,140", "change": "-", "avg": "$15,508", "todate": "$108,824,378", "week": "2"}, {"range": "Dec 4-10", "rank": "1", "weekly": "$25,937,161", "lw": "-46.7%", "theaters": "3,326", "change": "+186", "avg": "$7,798", "todate": "$134,761,539", "week": "3"}, {"range": "Dec 11-17", "rank": "2", "weekly": "$19,942,706", "lw": "-23.1%", "theaters": "3,388", "change": "+62", "avg": "$5,886", "todate": "$154,704,245", "week": "4"}, {"range": "Dec 18-24", "rank": "4", "weekly": "$17,972,391", "lw": "-9.9%", "theaters": "3,252", "change": "-136", "avg": "$5,526", "todate": "$172,676,636", "week": "5"}, {"range": "Dec 25-31", "rank": "5", "weekly": "$23,886,682", "lw": "+32.9%", "theaters": "2,766", "change": "-486", "avg": "$8,635", "todate": "$196,563,318", "week": "6"}, {"range": "Jan 1-7", "rank": "5", "weekly": "$14,883,591", "lw": "-37.7%", "theaters": "2,926", "change": "+160", "avg": "$5,086", "todate": "$211,446,909", "week": "7"}, {"range": "Jan 8-14", "rank": "7", "weekly": "$9,762,356", "lw": "-34.4%", "theaters": "2,880", "change": "-46", "avg": "$3,389", "todate": "$221,209,265", "week": "8"}, {"range": "Jan 15-21", "rank": "8", "weekly": "$8,303,001", "lw": "-14.9%", "theaters": "2,408", "change": "-472", "avg": "$3,448", "todate": "$229,512,266", "week": "9"}, {"range": "Jan 22-28", "rank": "11", "weekly": "$5,381,222", "lw": "-35.2%", "theaters": "1,932", "change": "-476", "avg": "$2,785", "todate": "$234,893,488", "week": "10"}, {"range": "Jan 29-Feb 4", "rank": "11", "weekly": "$4,132,881", "lw": "-23.2%", "theaters": "1,751", "change": "-181", "avg": "$2,360", "todate": "$239,026,369", "week": "11"}, {"range": "Feb 5-11", "rank": "11", "weekly": "$3,439,972", "lw": "-16.8%", "theaters": "1,740", "change": "-11", "avg": "$1,976", "todate": "$242,466,341", "week": "12"}, {"range": "Feb 12-18", "rank": "12", "weekly": "$3,153,611", "lw": "-8.3%", "theaters": "1,175", "change": "-565", "avg": "$2,683", "todate": "$245,619,952", "week": "13"}, {"range": "Feb 19-25", "rank": "13", "weekly": "$1,897,552", "lw": "-39.8%", "theaters": "1,060", "change": "-115", "avg": "$1,790", "todate": "$247,517,504", "week": "14"}, {"range": "Feb 26-Mar 4", "rank": "11", "weekly": "$1,692,357", "lw": "-10.8%", "theaters": "945", "change": "-115", "avg": "$1,790", "todate": "$249,209,861", "week": "15"}, {"range": "Mar 5-11", "rank": "13", "weekly": "$1,922,310", "lw": "+13.6%", "theaters": "822", "change": "-123", "avg": "$2,338", "todate": "$251,132,171", "week": "16"}, {"range": "Mar 12-18", "rank": "13", "weekly": "$2,264,074", "lw": "+17.8%", "theaters": "803", "change": "-19", "avg": "$2,819", "todate": "$253,396,245", "week": "17"}, {"range": "Mar 19-25", "rank": "17", "weekly": "$1,200,593", "lw": "-47%", "theaters": "602", "change": "-201", "avg": "$1,994", "todate": "$254,596,838", "week": "18"}, {"range": "Mar 26-Apr 1", "rank": "24", "weekly": "$666,290", "lw": "-44.5%", "theaters": "445", "change": "-157", "avg": "$1,497", "todate": "$255,263,128", "week": "19"}, {"range": "Apr 2-8", "rank": "24", "weekly": "$340,819", "lw": "-48.8%", "theaters": "316", "change": "-129", "avg": "$1,078", "todate": "$255,603,947", "week": "20"}, {"range": "Apr 9-15", "rank": "31", "weekly": "$174,098", "lw": "-48.9%", "theaters": "204", "change": "-112", "avg": "$853", "todate": "$255,778,045", "week": "21"}, {"range": "Apr 16-22", "rank": "41", "weekly": "$89,268", "lw": "-48.7%", "theaters": "123", "change": "-81", "avg": "$725", "todate": "$255,867,313", "week": "22"}, {"range": "Apr 23-29", "rank": "49", "weekly": "$43,130", "lw": "-51.7%", "theaters": "77", "change": "-46", "avg": "$560", "todate": "$255,910,443", "week": "23"}, {"range": "Apr 30-May 6", "rank": "63", "weekly": "$24,568", "lw": "-43%", "theaters": "46", "change": "-31", "avg": "$534", "todate": "$255,935,011", "week": "24"}, {"range": "May 7-13", "rank": "72", "weekly": "$12,979", "lw": "-47.2%", "theaters": "25", "change": "-21", "avg": "$519", "todate": "$255,947,990", "week": "25"}, {"range": "May 14-20", "rank": "93", "weekly": "$3,759", "lw": "-71%", "theaters": "11", "change": "-14", "avg": "$341", "todate": "$255,951,749", "week": "26"}, {"range": "May 21-27", "rank": "107", "weekly": "$1,555", "lw": "-58.6%", "theaters": "5", "change": "-6", "avg": "$311", "todate": "$255,953,304", "week": "27"}, {"range": "May 28-Jun 3", "rank": "81", "weekly": "$6,171", "lw": "+296.8%", "theaters": "5", "change": "-", "avg": "$1,234", "todate": "$255,959,475", "week": "28"}]