[{"range": "Feb 5-11", "rank": "66", "weekly": "$9,675", "lw": "-", "theaters": "1", "change": "-", "avg": "$9,675", "todate": "$9,675", "week": "1"}, {"range": "Feb 12-18", "rank": "67", "weekly": "$8,065", "lw": "-16.6%", "theaters": "1", "change": "-", "avg": "$8,065", "todate": "$17,740", "week": "2"}, {"range": "Feb 19-25", "rank": "85", "weekly": "$3,068", "lw": "-62%", "theaters": "1", "change": "-", "avg": "$3,068", "todate": "$20,808", "week": "3"}, {"range": "Feb 26-Mar 4", "rank": "85", "weekly": "$2,684", "lw": "-12.5%", "theaters": "1", "change": "-", "avg": "$2,684", "todate": "$23,492", "week": "4"}, {"range": "Mar 5-11", "rank": "88", "weekly": "$1,727", "lw": "-35.7%", "theaters": "1", "change": "-", "avg": "$1,727", "todate": "$25,219", "week": "5"}, {"range": "Mar 12-18", "rank": "104", "weekly": "$1,039", "lw": "-39.8%", "theaters": "1", "change": "-", "avg": "$1,039", "todate": "$26,258", "week": "6"}]