[{"range": "Sep 18-24", "rank": "79", "weekly": "$13,500", "lw": "-", "theaters": "1", "change": "-", "avg": "$13,500", "todate": "$13,500", "week": "1"}, {"range": "Oct 30-Nov 5", "rank": "122", "weekly": "$1,098", "lw": "-", "theaters": "1", "change": "-", "avg": "$1,098", "todate": "$14,598", "week": "7"}, {"range": "Nov 13-19", "rank": "123", "weekly": "$905", "lw": "-", "theaters": "1", "change": "-", "avg": "$905", "todate": "$15,503", "week": "9"}, {"range": "Jan 8-14", "rank": "73", "weekly": "$2,192", "lw": "-", "theaters": "1", "change": "-", "avg": "$2,192", "todate": "$17,695", "week": "17"}, {"range": "Feb 19-25", "rank": "94", "weekly": "$1,492", "lw": "-", "theaters": "1", "change": "-", "avg": "$1,492", "todate": "$19,187", "week": "23"}, {"range": "Feb 26-Mar 4", "rank": "102", "weekly": "$912", "lw": "-38.9%", "theaters": "1", "change": "-", "avg": "$912", "todate": "$20,099", "week": "24"}]