[{"range": "Nov 13-19", "rank": "1", "weekly": "$81,721,057", "lw": "-", "theaters": "3,404", "change": "-", "avg": "$24,007", "todate": "$81,721,057", "week": "1"}, {"range": "Nov 20-26", "rank": "3", "weekly": "$39,078,641", "lw": "-52.2%", "theaters": "3,444", "change": "+40", "avg": "$11,346", "todate": "$120,799,698", "week": "2"}, {"range": "Nov 27-Dec 3", "rank": "3", "weekly": "$21,387,123", "lw": "-45.3%", "theaters": "3,444", "change": "-", "avg": "$6,209", "todate": "$142,186,821", "week": "3"}, {"range": "Dec 4-10", "rank": "5", "weekly": "$8,750,019", "lw": "-59.1%", "theaters": "3,220", "change": "-224", "avg": "$2,717", "todate": "$150,936,840", "week": "4"}, {"range": "Dec 11-17", "rank": "7", "weekly": "$5,887,268", "lw": "-32.7%", "theaters": "2,838", "change": "-382", "avg": "$2,074", "todate": "$156,824,108", "week": "5"}, {"range": "Dec 18-24", "rank": "12", "weekly": "$3,672,078", "lw": "-37.6%", "theaters": "1,394", "change": "-1,444", "avg": "$2,634", "todate": "$160,496,186", "week": "6"}, {"range": "Dec 25-31", "rank": "15", "weekly": "$1,852,815", "lw": "-49.5%", "theaters": "800", "change": "-594", "avg": "$2,316", "todate": "$162,349,001", "week": "7"}, {"range": "Jan 1-7", "rank": "15", "weekly": "$1,388,785", "lw": "-25%", "theaters": "800", "change": "-", "avg": "$1,735", "todate": "$163,737,786", "week": "8"}, {"range": "Jan 8-14", "rank": "23", "weekly": "$485,919", "lw": "-65%", "theaters": "351", "change": "-449", "avg": "$1,384", "todate": "$164,223,705", "week": "9"}, {"range": "Jan 15-21", "rank": "21", "weekly": "$656,769", "lw": "+35.2%", "theaters": "373", "change": "+22", "avg": "$1,760", "todate": "$164,880,474", "week": "10"}, {"range": "Jan 22-28", "rank": "26", "weekly": "$439,816", "lw": "-33%", "theaters": "324", "change": "-49", "avg": "$1,357", "todate": "$165,320,290", "week": "11"}, {"range": "Jan 29-Feb 4", "rank": "30", "weekly": "$307,727", "lw": "-30%", "theaters": "272", "change": "-52", "avg": "$1,131", "todate": "$165,628,017", "week": "12"}, {"range": "Feb 5-11", "rank": "31", "weekly": "$225,431", "lw": "-26.7%", "theaters": "245", "change": "-27", "avg": "$920", "todate": "$165,853,448", "week": "13"}, {"range": "Feb 12-18", "rank": "34", "weekly": "$177,624", "lw": "-21.2%", "theaters": "173", "change": "-72", "avg": "$1,026", "todate": "$166,031,072", "week": "14"}, {"range": "Feb 19-25", "rank": "43", "weekly": "$81,095", "lw": "-54.3%", "theaters": "131", "change": "-42", "avg": "$619", "todate": "$166,112,167", "week": "15"}]