{"General Info": {"Distributor": "FUNimation Entertainment", "Opening": "$357,740", "Budget": ":", "Release Date": ["Oct 24, 2019", "-", "Nov 8, 2019"], "MPAA": ":", "Genres": ["Action", "Adventure", "Animation", "Family", "Fantasy"], "In Release": "71 days/10 weeks", "Widest Release": "541 theaters"}, "Weekly Income": [{"range": "Oct 18-24", "rank": "20", "weekly": "$413,015", "lw": "-", "theaters": "538", "change": "-", "avg": "$767", "todate": "$413,015", "week": "1"}, {"range": "Oct 25-31", "rank": "28", "weekly": "$357,740", "lw": "-13.4%", "theaters": "541", "change": "+3", "avg": "$661", "todate": "$770,755", "week": "2"}, {"range": "Nov 8-14", "rank": "53", "weekly": "$18,751", "lw": "-", "theaters": "-", "change": "-", "avg": "-", "todate": "$1,298,528", "week": "4"}]}