[{"range": "Jul 6-12", "rank": "90", "weekly": "$3,099", "lw": "-", "theaters": "1", "change": "-", "avg": "$3,099", "todate": "$3,099", "week": "1"}, {"range": "Jul 13-19", "rank": "55", "weekly": "$34,287", "lw": "+1,006.4%", "theaters": "2", "change": "+1", "avg": "$17,143", "todate": "$37,386", "week": "2"}, {"range": "Jul 20-26", "rank": "60", "weekly": "$24,218", "lw": "-29.4%", "theaters": "2", "change": "-", "avg": "$12,109", "todate": "$61,604", "week": "3"}, {"range": "Jul 27-Aug 2", "rank": "55", "weekly": "$31,080", "lw": "+28.3%", "theaters": "5", "change": "+3", "avg": "$6,216", "todate": "$92,684", "week": "4"}, {"range": "Aug 3-9", "rank": "61", "weekly": "$32,451", "lw": "+4.4%", "theaters": "6", "change": "+1", "avg": "$5,408", "todate": "$125,135", "week": "5"}, {"range": "Aug 10-16", "rank": "61", "weekly": "$27,456", "lw": "-15.4%", "theaters": "7", "change": "+1", "avg": "$3,922", "todate": "$152,591", "week": "6"}, {"range": "Aug 17-23", "rank": "71", "weekly": "$19,181", "lw": "-30.1%", "theaters": "5", "change": "-2", "avg": "$3,836", "todate": "$171,772", "week": "7"}, {"range": "Aug 24-30", "rank": "79", "weekly": "$12,929", "lw": "-32.6%", "theaters": "5", "change": "-", "avg": "$2,585", "todate": "$184,701", "week": "8"}, {"range": "Aug 31-Sep 6", "rank": "97", "weekly": "$3,566", "lw": "-72.4%", "theaters": "2", "change": "-3", "avg": "$1,783", "todate": "$188,267", "week": "9"}, {"range": "Sep 7-13", "rank": "115", "weekly": "$896", "lw": "-74.9%", "theaters": "2", "change": "-", "avg": "$448", "todate": "$189,163", "week": "10"}]