{"General Info": {"Distributor": "Walt Disney Studios Motion Pictures", "Opening": "$11,020,798", "Budget": ":", "Release Date": ["Feb 20, 2015", "-", "Jul 9, 2015"], "MPAA": "PG", "Genres": ["Biography", "Drama", "Sport"], "In Release": "315 days/45 weeks", "Widest Release": "$11,020,798"}, "Weekly Income": [{"range": "Feb 20-26", "rank": "4", "weekly": "$14,183,981", "lw": "-", "theaters": "2,755", "change": "-", "avg": "$5,148", "todate": "$14,183,981", "week": "1"}, {"range": "Feb 27-Mar 5", "rank": "6", "weekly": "$9,924,450", "lw": "-30%", "theaters": "2,765", "change": "+10", "avg": "$3,589", "todate": "$24,108,431", "week": "2"}, {"range": "Mar 6-12", "rank": "7", "weekly": "$7,173,676", "lw": "-27.7%", "theaters": "2,792", "change": "+27", "avg": "$2,569", "todate": "$31,282,107", "week": "3"}, {"range": "Mar 13-19", "rank": "8", "weekly": "$5,051,869", "lw": "-29.6%", "theaters": "2,455", "change": "-337", "avg": "$2,057", "todate": "$36,333,976", "week": "4"}, {"range": "Mar 20-26", "rank": "11", "weekly": "$3,107,720", "lw": "-38.5%", "theaters": "1,816", "change": "-639", "avg": "$1,711", "todate": "$39,441,696", "week": "5"}, {"range": "Mar 27-Apr 2", "rank": "12", "weekly": "$1,713,802", "lw": "-44.9%", "theaters": "1,126", "change": "-690", "avg": "$1,522", "todate": "$41,155,498", "week": "6"}, {"range": "Apr 3-9", "rank": "11", "weekly": "$1,029,005", "lw": "-40%", "theaters": "703", "change": "-423", "avg": "$1,463", "todate": "$42,184,503", "week": "7"}, {"range": "Apr 10-16", "rank": "15", "weekly": "$566,039", "lw": "-45%", "theaters": "518", "change": "-185", "avg": "$1,092", "todate": "$42,750,542", "week": "8"}, {"range": "Apr 17-23", "rank": "22", "weekly": "$291,356", "lw": "-48.5%", "theaters": "271", "change": "-247", "avg": "$1,075", "todate": "$43,041,898", "week": "9"}, {"range": "Apr 24-30", "rank": "28", "weekly": "$186,101", "lw": "-36.1%", "theaters": "182", "change": "-89", "avg": "$1,022", "todate": "$43,227,999", "week": "10"}, {"range": "May 1-7", "rank": "30", "weekly": "$120,420", "lw": "-35.3%", "theaters": "140", "change": "-42", "avg": "$860", "todate": "$43,348,419", "week": "11"}, {"range": "May 8-14", "rank": "27", "weekly": "$211,983", "lw": "+76%", "theaters": "128", "change": "-12", "avg": "$1,656", "todate": "$43,560,402", "week": "12"}, {"range": "May 15-21", "rank": "23", "weekly": "$283,974", "lw": "+34%", "theaters": "198", "change": "+70", "avg": "$1,434", "todate": "$43,844,376", "week": "13"}, {"range": "May 22-28", "rank": "23", "weekly": "$275,917", "lw": "-2.8%", "theaters": "171", "change": "-27", "avg": "$1,613", "todate": "$44,120,293", "week": "14"}, {"range": "May 29-Jun 4", "rank": "26", "weekly": "$156,548", "lw": "-43.3%", "theaters": "150", "change": "-21", "avg": "$1,043", "todate": "$44,276,841", "week": "15"}, {"range": "Jun 5-11", "rank": "31", "weekly": "$94,107", "lw": "-39.9%", "theaters": "103", "change": "-47", "avg": "$913", "todate": "$44,370,948", "week": "16"}, {"range": "Jun 12-18", "rank": "38", "weekly": "$61,011", "lw": "-35.2%", "theaters": "103", "change": "-", "avg": "$592", "todate": "$44,431,959", "week": "17"}, {"range": "Jun 19-25", "rank": "48", "weekly": "$25,890", "lw": "-57.6%", "theaters": "39", "change": "-64", "avg": "$663", "todate": "$44,457,849", "week": "18"}, {"range": "Jun 26-Jul 2", "rank": "60", "weekly": "$18,232", "lw": "-29.6%", "theaters": "21", "change": "-18", "avg": "$868", "todate": "$44,476,081", "week": "19"}, {"range": "Jul 3-9", "rank": "71", "weekly": "$6,329", "lw": "-65.3%", "theaters": "12", "change": "-9", "avg": "$527", "todate": "$44,482,410", "week": "20"}]}