[{"range": "Jan 13-19", "rank": "4", "weekly": "$15,827,982", "lw": "-", "theaters": "2,735", "change": "-", "avg": "$5,787", "todate": "$15,827,982", "week": "1"}, {"range": "Jan 20-26", "rank": "7", "weekly": "$7,659,528", "lw": "-51.6%", "theaters": "2,735", "change": "-", "avg": "$2,800", "todate": "$23,487,510", "week": "2"}, {"range": "Jan 27-Feb 2", "rank": "14", "weekly": "$4,017,718", "lw": "-47.5%", "theaters": "2,021", "change": "-714", "avg": "$1,987", "todate": "$27,505,228", "week": "3"}, {"range": "Feb 3-9", "rank": "17", "weekly": "$1,895,285", "lw": "-52.8%", "theaters": "1,350", "change": "-671", "avg": "$1,403", "todate": "$29,400,513", "week": "4"}, {"range": "Feb 10-16", "rank": "25", "weekly": "$687,446", "lw": "-63.7%", "theaters": "686", "change": "-664", "avg": "$1,002", "todate": "$30,087,959", "week": "5"}, {"range": "Feb 17-23", "rank": "37", "weekly": "$314,760", "lw": "-54.2%", "theaters": "340", "change": "-346", "avg": "$925", "todate": "$30,402,719", "week": "6"}, {"range": "Feb 24-Mar 1", "rank": "36", "weekly": "$250,594", "lw": "-20.4%", "theaters": "277", "change": "-63", "avg": "$904", "todate": "$30,653,313", "week": "7"}, {"range": "Mar 2-8", "rank": "40", "weekly": "$155,841", "lw": "-37.8%", "theaters": "202", "change": "-75", "avg": "$771", "todate": "$30,809,154", "week": "8"}, {"range": "Mar 9-15", "rank": "53", "weekly": "$81,236", "lw": "-47.9%", "theaters": "103", "change": "-99", "avg": "$788", "todate": "$30,890,390", "week": "9"}, {"range": "Mar 16-22", "rank": "66", "weekly": "$41,723", "lw": "-48.6%", "theaters": "65", "change": "-38", "avg": "$641", "todate": "$30,932,113", "week": "10"}]