[{"range": "Dec 16-22", "rank": "2", "weekly": "$36,940,187", "lw": "-", "theaters": "3,726", "change": "-", "avg": "$9,914", "todate": "$36,940,187", "week": "1"}, {"range": "Dec 23-29", "rank": "3", "weekly": "$39,419,148", "lw": "+6.7%", "theaters": "3,683", "change": "-43", "avg": "$10,702", "todate": "$76,359,335", "week": "2"}, {"range": "Dec 30-Jan 5, 2012", "rank": "3", "weekly": "$25,729,119", "lw": "-34.7%", "theaters": "3,724", "change": "+41", "avg": "$6,909", "todate": "$102,088,454", "week": "3"}, {"range": "Jan 6-12", "rank": "6", "weekly": "$10,892,834", "lw": "-57.7%", "theaters": "3,425", "change": "-299", "avg": "$3,180", "todate": "$112,981,288", "week": "4"}, {"range": "Jan 13-19", "rank": "9", "weekly": "$8,624,749", "lw": "-20.8%", "theaters": "2,849", "change": "-576", "avg": "$3,027", "todate": "$121,606,037", "week": "5"}, {"range": "Jan 20-26", "rank": "14", "weekly": "$3,653,285", "lw": "-57.6%", "theaters": "2,070", "change": "-779", "avg": "$1,764", "todate": "$125,259,322", "week": "6"}, {"range": "Jan 27-Feb 2", "rank": "19", "weekly": "$2,044,103", "lw": "-44%", "theaters": "1,070", "change": "-1,000", "avg": "$1,910", "todate": "$127,303,425", "week": "7"}, {"range": "Feb 3-9", "rank": "22", "weekly": "$1,216,429", "lw": "-40.5%", "theaters": "818", "change": "-252", "avg": "$1,487", "todate": "$128,519,854", "week": "8"}, {"range": "Feb 10-16", "rank": "26", "weekly": "$668,641", "lw": "-45%", "theaters": "502", "change": "-316", "avg": "$1,331", "todate": "$129,188,495", "week": "9"}, {"range": "Feb 17-23", "rank": "21", "weekly": "$819,015", "lw": "+22.5%", "theaters": "400", "change": "-102", "avg": "$2,047", "todate": "$130,007,510", "week": "10"}, {"range": "Feb 24-Mar 1", "rank": "25", "weekly": "$451,719", "lw": "-44.8%", "theaters": "311", "change": "-89", "avg": "$1,452", "todate": "$130,459,229", "week": "11"}, {"range": "Mar 2-8", "rank": "22", "weekly": "$441,112", "lw": "-2.3%", "theaters": "314", "change": "+3", "avg": "$1,404", "todate": "$130,900,341", "week": "12"}, {"range": "Mar 9-15", "rank": "25", "weekly": "$471,611", "lw": "+6.9%", "theaters": "287", "change": "-27", "avg": "$1,643", "todate": "$131,371,952", "week": "13"}, {"range": "Mar 16-22", "rank": "26", "weekly": "$402,036", "lw": "-14.8%", "theaters": "286", "change": "-1", "avg": "$1,405", "todate": "$131,773,988", "week": "14"}, {"range": "Mar 23-29", "rank": "25", "weekly": "$369,508", "lw": "-8.1%", "theaters": "248", "change": "-38", "avg": "$1,489", "todate": "$132,143,496", "week": "15"}, {"range": "Mar 30-Apr 5", "rank": "24", "weekly": "$372,439", "lw": "+0.8%", "theaters": "222", "change": "-26", "avg": "$1,677", "todate": "$132,515,935", "week": "16"}, {"range": "Apr 6-12", "rank": "30", "weekly": "$217,693", "lw": "-41.5%", "theaters": "195", "change": "-27", "avg": "$1,116", "todate": "$132,733,628", "week": "17"}, {"range": "Apr 13-19", "rank": "43", "weekly": "$119,734", "lw": "-45%", "theaters": "153", "change": "-42", "avg": "$782", "todate": "$132,853,362", "week": "18"}, {"range": "Apr 20-26", "rank": "46", "weekly": "$88,514", "lw": "-26.1%", "theaters": "135", "change": "-18", "avg": "$655", "todate": "$132,941,876", "week": "19"}, {"range": "Apr 27-May 3", "rank": "52", "weekly": "$63,511", "lw": "-28.2%", "theaters": "111", "change": "-24", "avg": "$572", "todate": "$133,005,387", "week": "20"}, {"range": "May 4-10", "rank": "62", "weekly": "$36,562", "lw": "-42.4%", "theaters": "75", "change": "-36", "avg": "$487", "todate": "$133,041,949", "week": "21"}, {"range": "May 11-17", "rank": "66", "weekly": "$29,824", "lw": "-18.4%", "theaters": "67", "change": "-8", "avg": "$445", "todate": "$133,071,773", "week": "22"}, {"range": "May 18-24", "rank": "68", "weekly": "$17,315", "lw": "-41.9%", "theaters": "40", "change": "-27", "avg": "$432", "todate": "$133,089,088", "week": "23"}, {"range": "May 25-31", "rank": "74", "weekly": "$11,828", "lw": "-31.7%", "theaters": "22", "change": "-18", "avg": "$537", "todate": "$133,100,916", "week": "24"}, {"range": "Jun 1-7", "rank": "75", "weekly": "$9,826", "lw": "-16.9%", "theaters": "14", "change": "-8", "avg": "$701", "todate": "$133,110,742", "week": "25"}]