[{"range": "May 2-8", "rank": "34", "weekly": "$133,174", "lw": "-", "theaters": "30", "change": "-", "avg": "$4,439", "todate": "$133,174", "week": "1"}, {"range": "May 9-15", "rank": "32", "weekly": "$120,848", "lw": "-9.3%", "theaters": "38", "change": "+8", "avg": "$3,180", "todate": "$254,022", "week": "2"}, {"range": "May 16-22", "rank": "37", "weekly": "$109,830", "lw": "-9.1%", "theaters": "34", "change": "-4", "avg": "$3,230", "todate": "$363,852", "week": "3"}, {"range": "May 23-29", "rank": "50", "weekly": "$53,810", "lw": "-51%", "theaters": "26", "change": "-8", "avg": "$2,069", "todate": "$417,662", "week": "4"}, {"range": "May 30-Jun 5", "rank": "52", "weekly": "$40,789", "lw": "-24.2%", "theaters": "26", "change": "-", "avg": "$1,568", "todate": "$458,451", "week": "5"}, {"range": "Jun 6-12", "rank": "61", "weekly": "$25,834", "lw": "-36.7%", "theaters": "18", "change": "-8", "avg": "$1,435", "todate": "$484,285", "week": "6"}, {"range": "Jun 13-19", "rank": "58", "weekly": "$27,287", "lw": "+5.6%", "theaters": "19", "change": "+1", "avg": "$1,436", "todate": "$511,572", "week": "7"}, {"range": "Jun 20-26", "rank": "56", "weekly": "$27,113", "lw": "-0.6%", "theaters": "15", "change": "-4", "avg": "$1,807", "todate": "$538,685", "week": "8"}, {"range": "Jun 27-Jul 3", "rank": "62", "weekly": "$22,902", "lw": "-15.5%", "theaters": "15", "change": "-", "avg": "$1,526", "todate": "$561,587", "week": "9"}, {"range": "Jul 4-10", "rank": "61", "weekly": "$21,099", "lw": "-7.9%", "theaters": "14", "change": "-1", "avg": "$1,507", "todate": "$582,686", "week": "10"}, {"range": "Jul 11-17", "rank": "62", "weekly": "$19,336", "lw": "-8.4%", "theaters": "18", "change": "+4", "avg": "$1,074", "todate": "$602,022", "week": "11"}, {"range": "Jul 18-24", "rank": "74", "weekly": "$11,427", "lw": "-40.9%", "theaters": "13", "change": "-5", "avg": "$879", "todate": "$613,449", "week": "12"}, {"range": "Jul 25-31", "rank": "80", "weekly": "$11,363", "lw": "-0.6%", "theaters": "14", "change": "+1", "avg": "$811", "todate": "$624,812", "week": "13"}, {"range": "Aug 1-7", "rank": "96", "weekly": "$6,149", "lw": "-45.9%", "theaters": "7", "change": "-7", "avg": "$878", "todate": "$630,961", "week": "14"}, {"range": "Aug 8-14", "rank": "94", "weekly": "$4,822", "lw": "-21.6%", "theaters": "7", "change": "-", "avg": "$688", "todate": "$635,783", "week": "15"}]