{"General Info": {"Distributor": "Paramount Pictures", "Opening": "$129,462", "Budget": "$24,000,000", "Release Date": ":(", "MPAA": "PG-13", "Genres": ["Drama"], "In Release": "381 days/54 weeks", "Widest Release": "2,368 theaters"}, "Weekly Income": [{"range": "Dec 16-22", "rank": "29", "weekly": "$191,515", "lw": "-", "theaters": "4", "change": "-", "avg": "$47,878", "todate": "$191,515", "week": "1"}, {"range": "Dec 23-29", "rank": "7", "weekly": "$19,510,629", "lw": "+10,087.5%", "theaters": "2,233", "change": "+2,229", "avg": "$8,737", "todate": "$19,702,144", "week": "2"}, {"range": "Dec 30-Jan 5, 2017", "rank": "7", "weekly": "$16,261,120", "lw": "-16.7%", "theaters": "2,301", "change": "+68", "avg": "$7,066", "todate": "$35,963,264", "week": "3"}, {"range": "Jan 6-12", "rank": "9", "weekly": "$7,169,098", "lw": "-55.9%", "theaters": "2,368", "change": "+67", "avg": "$3,027", "todate": "$43,132,362", "week": "4"}, {"range": "Jan 13-19", "rank": "14", "weekly": "$4,367,322", "lw": "-39.1%", "theaters": "1,342", "change": "-1,026", "avg": "$3,254", "todate": "$47,499,684", "week": "5"}, {"range": "Jan 20-26", "rank": "18", "weekly": "$1,879,925", "lw": "-57%", "theaters": "693", "change": "-649", "avg": "$2,712", "todate": "$49,379,609", "week": "6"}, {"range": "Jan 27-Feb 2", "rank": "19", "weekly": "$2,046,411", "lw": "+8.9%", "theaters": "880", "change": "+187", "avg": "$2,325", "todate": "$51,426,020", "week": "7"}, {"range": "Feb 3-9", "rank": "16", "weekly": "$1,794,707", "lw": "-12.3%", "theaters": "948", "change": "+68", "avg": "$1,893", "todate": "$53,220,727", "week": "8"}, {"range": "Feb 10-16", "rank": "16", "weekly": "$1,126,242", "lw": "-37.2%", "theaters": "454", "change": "-494", "avg": "$2,480", "todate": "$54,346,969", "week": "9"}, {"range": "Feb 17-23", "rank": "17", "weekly": "$1,429,319", "lw": "+26.9%", "theaters": "597", "change": "+143", "avg": "$2,394", "todate": "$55,776,288", "week": "10"}, {"range": "Feb 24-Mar 2", "rank": "18", "weekly": "$1,035,497", "lw": "-27.6%", "theaters": "597", "change": "-", "avg": "$1,734", "todate": "$56,811,785", "week": "11"}, {"range": "Mar 3-9", "rank": "25", "weekly": "$426,694", "lw": "-58.8%", "theaters": "284", "change": "-313", "avg": "$1,502", "todate": "$57,238,479", "week": "12"}, {"range": "Mar 10-16", "rank": "29", "weekly": "$232,233", "lw": "-45.6%", "theaters": "189", "change": "-95", "avg": "$1,228", "todate": "$57,470,712", "week": "13"}, {"range": "Mar 17-23", "rank": "35", "weekly": "$96,156", "lw": "-58.6%", "theaters": "94", "change": "-95", "avg": "$1,022", "todate": "$57,566,868", "week": "14"}, {"range": "Mar 24-30", "rank": "39", "weekly": "$116,036", "lw": "+20.7%", "theaters": "111", "change": "+17", "avg": "$1,045", "todate": "$57,682,904", "week": "15"}]}