{"General Info": {"Distributor": "Vertical Entertainment", "Opening": "$36,997", "Budget": ":", "Release Date": ["Sep 9, 2016", "-", "Oct 13, 2016"], "MPAA": ":", "Genres": ["Comedy", "Drama"], "In Release": "114 days/16 weeks", "Widest Release": "12 theaters"}, "Weekly Income": [{"range": "Sep 9-15", "rank": "54", "weekly": "$48,682", "lw": "-", "theaters": "12", "change": "-", "avg": "$4,056", "todate": "$48,682", "week": "1"}, {"range": "Sep 16-22", "rank": "75", "weekly": "$20,751", "lw": "-57.4%", "theaters": "8", "change": "-4", "avg": "$2,593", "todate": "$69,433", "week": "2"}, {"range": "Sep 23-29", "rank": "66", "weekly": "$16,074", "lw": "-22.5%", "theaters": "12", "change": "+4", "avg": "$1,339", "todate": "$85,507", "week": "3"}, {"range": "Sep 30-Oct 6", "rank": "100", "weekly": "$4,890", "lw": "-69.6%", "theaters": "4", "change": "-8", "avg": "$1,222", "todate": "$90,397", "week": "4"}, {"range": "Oct 7-13", "rank": "125", "weekly": "$1,044", "lw": "-78.7%", "theaters": "2", "change": "-2", "avg": "$522", "todate": "$91,441", "week": "5"}]}