{"General Info": {"Distributor": "FilmRise", "Opening": "$3,270", "Budget": ":", "Release Date": ["May 6, 2016", "-", "Jun 9, 2016"], "MPAA": ":", "Genres": ["Documentary"], "In Release": "240 days/34 weeks", "Widest Release": "14 theaters"}, "Weekly Income": [{"range": "May 6-12", "rank": "89", "weekly": "$6,093", "lw": "-", "theaters": "14", "change": "-", "avg": "$435", "todate": "$6,093", "week": "1"}, {"range": "May 13-19", "rank": "111", "weekly": "$2,177", "lw": "-64.3%", "theaters": "3", "change": "-11", "avg": "$725", "todate": "$8,270", "week": "2"}, {"range": "May 20-26", "rank": "110", "weekly": "$1,954", "lw": "-10.2%", "theaters": "2", "change": "-1", "avg": "$977", "todate": "$10,224", "week": "3"}, {"range": "May 27-Jun 2", "rank": "105", "weekly": "$1,157", "lw": "-40.8%", "theaters": "3", "change": "+1", "avg": "$385", "todate": "$11,381", "week": "4"}, {"range": "Jun 3-9", "rank": "104", "weekly": "$792", "lw": "-31.5%", "theaters": "2", "change": "-1", "avg": "$396", "todate": "$12,173", "week": "5"}]}