{"General Info": {"Distributor": "Sony Pictures Entertainment (SPE)", "Opening": "$14,860,425", "Budget": "$75,000,000", "Release Date": ["Oct 28, 2016", "-", "Jan 19, 2017"], "MPAA": "PG-13", "Genres": ["Action", "Adventure", "Crime", "Drama", "Mystery", "Thriller"], "In Release": "430 days/61 weeks", "Widest Release": "3,576 theaters"}, "Weekly Income": [{"range": "Oct 28-Nov 3", "rank": "2", "weekly": "$19,807,930", "lw": "-", "theaters": "3,576", "change": "-", "avg": "$5,539", "todate": "$19,807,930", "week": "1"}, {"range": "Nov 4-10", "rank": "5", "weekly": "$8,524,085", "lw": "-57%", "theaters": "3,576", "change": "-", "avg": "$2,383", "todate": "$28,332,015", "week": "2"}, {"range": "Nov 11-17", "rank": "9", "weekly": "$4,401,458", "lw": "-48.4%", "theaters": "2,656", "change": "-920", "avg": "$1,657", "todate": "$32,733,473", "week": "3"}, {"range": "Nov 18-24", "rank": "19", "weekly": "$897,880", "lw": "-79.6%", "theaters": "165", "change": "-2,491", "avg": "$5,441", "todate": "$33,631,353", "week": "4"}, {"range": "Nov 25-Dec 1", "rank": "29", "weekly": "$218,723", "lw": "-75.6%", "theaters": "165", "change": "-", "avg": "$1,325", "todate": "$33,850,076", "week": "5"}, {"range": "Dec 2-8", "rank": "33", "weekly": "$137,346", "lw": "-37.2%", "theaters": "154", "change": "-11", "avg": "$891", "todate": "$33,987,422", "week": "6"}, {"range": "Dec 9-15", "rank": "34", "weekly": "$92,539", "lw": "-32.6%", "theaters": "128", "change": "-26", "avg": "$722", "todate": "$34,079,961", "week": "7"}, {"range": "Dec 16-22", "rank": "49", "weekly": "$27,386", "lw": "-70.4%", "theaters": "43", "change": "-85", "avg": "$636", "todate": "$34,107,347", "week": "8"}, {"range": "Dec 23-29", "rank": "38", "weekly": "$84,919", "lw": "+210.1%", "theaters": "102", "change": "+59", "avg": "$832", "todate": "$34,192,266", "week": "9"}, {"range": "Dec 30-Jan 5, 2017", "rank": "39", "weekly": "$81,929", "lw": "-3.5%", "theaters": "102", "change": "-", "avg": "$803", "todate": "$34,274,195", "week": "10"}, {"range": "Jan 6-12", "rank": "45", "weekly": "$48,239", "lw": "-41.1%", "theaters": "83", "change": "-19", "avg": "$581", "todate": "$34,322,434", "week": "11"}, {"range": "Jan 13-19", "rank": "51", "weekly": "$21,140", "lw": "-56.2%", "theaters": "83", "change": "-", "avg": "$254", "todate": "$34,343,574", "week": "12"}]}