{"General Info": {"Distributor": "Universal Pictures", "Opening": "$8,571,785", "Budget": "$35,000,000", "Release Date": ["Sep 16, 2016", "-", "Dec 15, 2016"], "MPAA": "R", "Genres": ["Comedy", "Drama", "Romance"], "In Release": "112 days/16 weeks", "Widest Release": "2,930 theaters"}, "Weekly Income": [{"range": "Sep 16-22", "rank": "3", "weekly": "$11,937,675", "lw": "-", "theaters": "2,927", "change": "-", "avg": "$4,078", "todate": "$11,937,675", "week": "1"}, {"range": "Sep 23-29", "rank": "4", "weekly": "$6,714,060", "lw": "-43.8%", "theaters": "2,050", "change": "-877", "avg": "$3,275", "todate": "$18,651,735", "week": "2"}, {"range": "Sep 30-Oct 6", "rank": "8", "weekly": "$3,308,960", "lw": "-50.7%", "theaters": "2,055", "change": "+5", "avg": "$1,610", "todate": "$21,960,695", "week": "3"}, {"range": "Oct 7-13", "rank": "13", "weekly": "$1,289,890", "lw": "-61%", "theaters": "915", "change": "-1,140", "avg": "$1,409", "todate": "$23,250,585", "week": "4"}, {"range": "Oct 14-20", "rank": "21", "weekly": "$524,555", "lw": "-59.3%", "theaters": "390", "change": "-525", "avg": "$1,345", "todate": "$23,775,140", "week": "5"}, {"range": "Oct 21-27", "rank": "30", "weekly": "$225,065", "lw": "-57.1%", "theaters": "172", "change": "-218", "avg": "$1,308", "todate": "$24,000,205", "week": "6"}, {"range": "Oct 28-Nov 3", "rank": "36", "weekly": "$139,600", "lw": "-38%", "theaters": "132", "change": "-40", "avg": "$1,057", "todate": "$24,139,805", "week": "7"}, {"range": "Nov 4-10", "rank": "46", "weekly": "$60,235", "lw": "-56.9%", "theaters": "60", "change": "-72", "avg": "$1,003", "todate": "$24,200,040", "week": "8"}, {"range": "Nov 11-17", "rank": "55", "weekly": "$35,450", "lw": "-41.1%", "theaters": "40", "change": "-20", "avg": "$886", "todate": "$24,235,490", "week": "9"}, {"range": "Nov 18-24", "rank": "69", "weekly": "$11,710", "lw": "-67%", "theaters": "22", "change": "-18", "avg": "$532", "todate": "$24,247,200", "week": "10"}, {"range": "Nov 25-Dec 1", "rank": "85", "weekly": "$2,480", "lw": "-78.8%", "theaters": "7", "change": "-15", "avg": "$354", "todate": "$24,249,680", "week": "11"}, {"range": "Dec 2-8", "rank": "115", "weekly": "$1,410", "lw": "-43.1%", "theaters": "4", "change": "-3", "avg": "$352", "todate": "$24,251,090", "week": "12"}, {"range": "Dec 9-15", "rank": "97", "weekly": "$1,330", "lw": "-5.7%", "theaters": "3", "change": "-1", "avg": "$443", "todate": "$24,252,420", "week": "13"}]}