{"General Info": {"Distributor": "A24", "Opening": "$12,247", "Budget": ":", "Release Date": ["Sep 22, 2017", "-", "Oct 12, 2017"], "MPAA": "R", "Genres": ["Drama", "Fantasy", "Horror", "Thriller"], "In Release": "101 days/14 weeks", "Widest Release": "39 theaters"}, "Weekly Income": [{"range": "Sep 22-28", "rank": "65", "weekly": "$15,908", "lw": "-", "theaters": "3", "change": "-", "avg": "$5,302", "todate": "$15,908", "week": "1"}, {"range": "Sep 29-Oct 5", "rank": "58", "weekly": "$23,811", "lw": "+49.7%", "theaters": "39", "change": "+36", "avg": "$610", "todate": "$39,719", "week": "2"}, {"range": "Oct 6-12", "rank": "106", "weekly": "$2,884", "lw": "-87.9%", "theaters": "9", "change": "-30", "avg": "$320", "todate": "$42,603", "week": "3"}]}