{"General Info": {"Distributor": "First Run", "Opening": "$6,636", "Budget": ":", "Release Date": ["Nov 29, 2017", "-", "Dec 17, 2017"], "MPAA": ":", "Genres": ["Documentary", "War"], "In Release": "37 days/5 weeks", "Widest Release": "2 theaters"}, "Weekly Income": [{"range": "Dec 1-7", "rank": "60", "weekly": "$14,883", "lw": "-", "theaters": "1", "change": "-", "avg": "$14,883", "todate": "$14,883", "week": "2"}, {"range": "Dec 8-14", "rank": "67", "weekly": "$8,261", "lw": "-44.5%", "theaters": "2", "change": "+1", "avg": "$4,130", "todate": "$23,144", "week": "3"}]}