{"General Info": {"Distributor": "Open Road Films (II)", "Opening": "$4,690,214", "Budget": ":", "Release Date": ["Mar 3, 2017", "-", "Apr 27, 2017"], "MPAA": "PG-13", "Genres": ["Drama", "Fantasy", "Mystery"], "In Release": "304 days/43 weeks", "Widest Release": "2,346 theaters"}, "Weekly Income": [{"range": "Mar 3-9", "rank": "6", "weekly": "$5,928,812", "lw": "-", "theaters": "2,346", "change": "-", "avg": "$2,527", "todate": "$5,928,812", "week": "1"}, {"range": "Mar 10-16", "rank": "6", "weekly": "$4,331,865", "lw": "-26.9%", "theaters": "2,346", "change": "-", "avg": "$1,846", "todate": "$10,260,677", "week": "2"}, {"range": "Mar 17-23", "rank": "10", "weekly": "$1,447,113", "lw": "-66.6%", "theaters": "1,551", "change": "-795", "avg": "$933", "todate": "$11,707,790", "week": "3"}, {"range": "Mar 24-30", "rank": "26", "weekly": "$301,810", "lw": "-79.1%", "theaters": "351", "change": "-1,200", "avg": "$859", "todate": "$12,009,600", "week": "4"}, {"range": "Mar 31-Apr 6", "rank": "45", "weekly": "$56,613", "lw": "-81.2%", "theaters": "98", "change": "-253", "avg": "$577", "todate": "$12,066,213", "week": "5"}, {"range": "Apr 7-13", "rank": "38", "weekly": "$104,102", "lw": "+83.9%", "theaters": "268", "change": "+170", "avg": "$388", "todate": "$12,170,315", "week": "6"}, {"range": "Apr 14-20", "rank": "51", "weekly": "$36,729", "lw": "-64.7%", "theaters": "70", "change": "-198", "avg": "$524", "todate": "$12,207,044", "week": "7"}, {"range": "Apr 21-27", "rank": "51", "weekly": "$34,078", "lw": "-7.2%", "theaters": "70", "change": "-", "avg": "$486", "todate": "$12,241,122", "week": "8"}]}