{"General Info": {"Distributor": "Kino Lorber", "Opening": "$1,011", "Budget": ":", "Release Date": ["Apr 14, 2017", "-", "Jun 15, 2017"], "MPAA": ":", "Genres": ["Adventure", "Comedy", "Drama"], "In Release": "262 days/37 weeks", "Widest Release": "2 theaters"}, "Weekly Income": [{"range": "Apr 14-20", "rank": "105", "weekly": "$1,011", "lw": "-", "theaters": "1", "change": "-", "avg": "$1,011", "todate": "$1,011", "week": "1"}, {"range": "Apr 21-27", "rank": "97", "weekly": "$2,070", "lw": "+104.7%", "theaters": "1", "change": "-", "avg": "$2,070", "todate": "$3,081", "week": "2"}, {"range": "Apr 28-May 4", "rank": "109", "weekly": "$732", "lw": "-64.6%", "theaters": "1", "change": "-", "avg": "$732", "todate": "$3,813", "week": "3"}, {"range": "May 5-11", "rank": "113", "weekly": "$351", "lw": "-52%", "theaters": "1", "change": "-", "avg": "$351", "todate": "$4,164", "week": "4"}, {"range": "May 12-18", "rank": "112", "weekly": "$932", "lw": "+165.5%", "theaters": "1", "change": "-", "avg": "$932", "todate": "$5,096", "week": "5"}, {"range": "May 26-Jun 1", "rank": "94", "weekly": "$1,752", "lw": "-", "theaters": "1", "change": "-", "avg": "$1,752", "todate": "$6,848", "week": "7"}, {"range": "Jun 2-8", "rank": "113", "weekly": "$404", "lw": "-76.9%", "theaters": "2", "change": "+1", "avg": "$202", "todate": "$7,252", "week": "8"}, {"range": "Jun 9-15", "rank": "105", "weekly": "$624", "lw": "+54.5%", "theaters": "2", "change": "-", "avg": "$312", "todate": "$7,876", "week": "9"}]}