{"General Info": {"Distributor": "The Cinema Guild", "Opening": "$707", "Budget": ":", "Release Date": ["Jan 20, 2017", "-", "Jul 2, 2017"], "MPAA": ":", "Genres": ["Documentary"], "In Release": "346 days/49 weeks", "Widest Release": "2 theaters"}, "Weekly Income": [{"range": "Jan 20-26", "rank": "91", "weekly": "$707", "lw": "-", "theaters": "1", "change": "-", "avg": "$707", "todate": "$707", "week": "1"}, {"range": "Jan 27-Feb 2", "rank": "87", "weekly": "$1,247", "lw": "+76.4%", "theaters": "2", "change": "+1", "avg": "$623", "todate": "$1,954", "week": "2"}]}