{"General Info": {"Distributor": "FUNimation Entertainment", "Opening": "$169,203", "Budget": ":", "Release Date": ["Aug 14, 2017", "-", "Aug 20, 2017"], "MPAA": ":", "Genres": ["Action", "Adventure", "Animation", "Comedy", "Fantasy"], "In Release": "140 days/20 weeks", "Widest Release": "304 theaters"}, "Weekly Income": [{"range": "Aug 11-17", "rank": "28", "weekly": "$350,258", "lw": "-", "theaters": "16", "change": "-", "avg": "$21,891", "todate": "$350,258", "week": "1"}, {"range": "Aug 18-24", "rank": "36", "weekly": "$169,203", "lw": "-51.7%", "theaters": "292", "change": "+276", "avg": "$579", "todate": "$519,461", "week": "2"}]}