{"General Info": {"Distributor": "Atlas Distribution Company", "Opening": "$34,437", "Budget": ":", "Release Date": ["Jan 12, 2018", "-", "Feb 8, 2018"], "MPAA": ":", "Genres": ["Action", "Comedy", "Crime"], "In Release": "354 days/50 weeks", "Widest Release": "39 theaters"}, "Weekly Income": [{"range": "Jan 12-18", "rank": "44", "weekly": "$48,867", "lw": "-", "theaters": "24", "change": "-", "avg": "$2,036", "todate": "$48,867", "week": "1"}, {"range": "Jan 19-25", "rank": "60", "weekly": "$13,661", "lw": "-72%", "theaters": "3", "change": "-21", "avg": "$4,553", "todate": "$62,528", "week": "2"}, {"range": "Jan 26-Feb 1", "rank": "83", "weekly": "$5,490", "lw": "-59.8%", "theaters": "1", "change": "-2", "avg": "$5,490", "todate": "$68,018", "week": "3"}, {"range": "Feb 2-8", "rank": "91", "weekly": "$1,413", "lw": "-74.3%", "theaters": "1", "change": "-", "avg": "$1,413", "todate": "$69,431", "week": "4"}]}