{"General Info": {"Distributor": "Indican Pictures", "Opening": "$4,505", "Budget": ":", "Release Date": ["Jul 27, 2018", "-", "Sep 6, 2018"], "MPAA": ":", "Genres": ["Comedy", "Crime", "Mystery"], "In Release": "158 days/22 weeks", "Widest Release": "5 theaters"}, "Weekly Income": [{"range": "Jul 27-Aug 2", "rank": "75", "weekly": "$9,515", "lw": "-", "theaters": "5", "change": "-", "avg": "$1,903", "todate": "$9,515", "week": "1"}, {"range": "Aug 3-9", "rank": "84", "weekly": "$3,876", "lw": "-59.3%", "theaters": "4", "change": "-1", "avg": "$969", "todate": "$13,391", "week": "2"}, {"range": "Aug 10-16", "rank": "94", "weekly": "$1,292", "lw": "-66.7%", "theaters": "4", "change": "-", "avg": "$323", "todate": "$14,683", "week": "3"}, {"range": "Aug 17-23", "rank": "92", "weekly": "$3,321", "lw": "+157%", "theaters": "3", "change": "-1", "avg": "$1,107", "todate": "$18,004", "week": "4"}, {"range": "Aug 24-30", "rank": "97", "weekly": "$3,372", "lw": "+1.5%", "theaters": "3", "change": "-", "avg": "$1,124", "todate": "$21,376", "week": "5"}, {"range": "Aug 31-Sep 6", "rank": "111", "weekly": "$813", "lw": "-75.9%", "theaters": "3", "change": "-", "avg": "$271", "todate": "$22,189", "week": "6"}]}